pydantic_config_builder/__init__.py
pydantic_config_builder/builder.py
pydantic_config_builder/cli.py
pydantic_config_builder/config.py
pydantic_config_builder/py.typed
pydantic_config_builder-0.5.1.dist-info/LICENSE
pydantic_config_builder-0.5.1.dist-info/METADATA
pydantic_config_builder-0.5.1.dist-info/WHEEL
pydantic_config_builder-0.5.1.dist-info/entry_points.txt
pydantic_config_builder-0.5.1.dist-info/RECORD
