Metadata-Version: 2.3
Name: pydantic-config-builder
Version: 0.5.1
Summary: A tool to build YAML configurations by merging multiple files
License: MIT
Keywords: pydantic,yaml,configuration,builder
Author: kiarina
Author-email: kiarinadawa@gmail.com
Requires-Python: >=3.8,<4.0
Classifier: Development Status :: 4 - Beta
Classifier: Intended Audience :: Developers
Classifier: License :: OSI Approved :: MIT License
Classifier: Operating System :: OS Independent
Classifier: Programming Language :: Python :: 3
Classifier: Programming Language :: Python :: 3.8
Classifier: Programming Language :: Python :: 3.9
Classifier: Programming Language :: Python :: 3.10
Classifier: Programming Language :: Python :: 3.11
Classifier: Programming Language :: Python :: 3.12
Classifier: Programming Language :: Python :: 3.13
Classifier: Topic :: Software Development :: Libraries :: Python Modules
Requires-Dist: PyYAML (>=6.0.0,<7.0.0)
Requires-Dist: click (>=8.0.0,<9.0.0)
Requires-Dist: pydantic (>=2.0.0,<3.0.0)
Project-URL: Documentation, https://github.com/kiarina/pydantic-config-builder
Project-URL: Homepage, https://github.com/kiarina/pydantic-config-builder
Project-URL: Repository, https://github.com/kiarina/pydantic-config-builder
